LICENSE
MANIFEST.in
README.md
package.json
setup.py
thinks_dash_url_observer/ThinksDashURLObserver.py
thinks_dash_url_observer/__init__.py
thinks_dash_url_observer/_imports_.py
thinks_dash_url_observer/metadata.json
thinks_dash_url_observer/package-info.json
thinks_dash_url_observer/thinks_dash_url_observer.min.js
thinks_dash_url_observer/thinks_dash_url_observer.min.js.map
thinks_dash_url_observer.egg-info/PKG-INFO
thinks_dash_url_observer.egg-info/SOURCES.txt
thinks_dash_url_observer.egg-info/dependency_links.txt
thinks_dash_url_observer.egg-info/top_level.txt